github_index/__init__.py
github_index/badge.py
github_index/get_repository_data.py
github_index/main.py
github_index/metadata_validation.py
github_index/project_pages.py
github_index/readme_validation.py
github_index-0.1.3.dist-info/licenses/LICENSE
github_index-0.1.3.dist-info/METADATA
github_index-0.1.3.dist-info/WHEEL
github_index-0.1.3.dist-info/top_level.txt
github_index-0.1.3.dist-info/RECORD
