Metadata-Version: 2.4
Name: github_index
Version: 0.1.3
Summary: Creates a index with repositories from Github.
Author-email: "H.IAAC" <hiaac@unicamp.br>, Elton Cardoso do Nascimento <e233840@dac.unicamp.br>
Project-URL: Homepage, https://hiaac.unicamp.br
Classifier: Programming Language :: Python :: 3
Classifier: Operating System :: OS Independent
Classifier: Intended Audience :: Developers
Classifier: Topic :: Documentation
Classifier: Topic :: Software Development :: Documentation
Classifier: License :: OSI Approved :: GNU Lesser General Public License v3 (LGPLv3)
Requires-Python: >=3.10
License-File: LICENSE
Requires-Dist: pandas
Requires-Dist: requests
Requires-Dist: tqdm
Requires-Dist: marko
Requires-Dist: cffconvert
Dynamic: license-file
